goflask/__init__.py
goflask/_version.py
goflask/cli.py
goflask/context.py
goflask/core.py
goflask/exceptions.py
goflask/helpers.py
goflask-1.0.0.dist-info/licenses/LICENSE
goflask-1.0.0.dist-info/METADATA
goflask-1.0.0.dist-info/WHEEL
goflask-1.0.0.dist-info/entry_points.txt
goflask-1.0.0.dist-info/top_level.txt
goflask-1.0.0.dist-info/RECORD
