Metadata-Version: 2.4
Name: goflask
Version: 1.0.0
Summary: High-performance Flask-compatible web framework powered by Go
Home-page: https://github.com/coffeecms/goflask
Author: GoFlask Team
Author-email: GoFlask Team <team@goflask.org>
Maintainer-email: GoFlask Team <team@goflask.org>
License: MIT
Project-URL: Homepage, https://github.com/goflask/goflask
Project-URL: Documentation, https://goflask.readthedocs.io
Project-URL: Repository, https://github.com/goflask/goflask
Project-URL: Bug Tracker, https://github.com/goflask/goflask/issues
Project-URL: Changelog, https://github.com/goflask/goflask/blob/main/CHANGELOG.md
Project-URL: Funding, https://github.com/sponsors/goflask
Keywords: web,framework,flask,go,performance,api,rest,microservice,wsgi,asgi
Classifier: Development Status :: 5 - Production/Stable
Classifier: Intended Audience :: Developers
Classifier: License :: OSI Approved :: MIT License
Classifier: Operating System :: OS Independent
Classifier: Programming Language :: Python :: 3
Classifier: Programming Language :: Python :: 3.7
Classifier: Programming Language :: Python :: 3.8
Classifier: Programming Language :: Python :: 3.9
Classifier: Programming Language :: Python :: 3.10
Classifier: Programming Language :: Python :: 3.11
Classifier: Programming Language :: Python :: 3.12
Classifier: Programming Language :: Go
Classifier: Topic :: Internet :: WWW/HTTP :: Dynamic Content
Classifier: Topic :: Internet :: WWW/HTTP :: WSGI :: Application
Classifier: Topic :: Software Development :: Libraries :: Application Frameworks
Classifier: Topic :: Software Development :: Libraries :: Python Modules
Classifier: Framework :: Flask
Classifier: Environment :: Web Environment
Classifier: Typing :: Typed
Requires-Python: >=3.7
License-File: LICENSE
Requires-Dist: typing-extensions>=4.0.0; python_version < "3.10"
Provides-Extra: cli
Requires-Dist: click>=8.0.0; extra == "cli"
Provides-Extra: dev
Requires-Dist: werkzeug>=2.0.0; extra == "dev"
Provides-Extra: redis
Requires-Dist: redis>=4.0.0; extra == "redis"
Provides-Extra: logging
Requires-Dist: structlog>=22.0.0; extra == "logging"
Provides-Extra: fast-json
Requires-Dist: orjson>=3.8.0; extra == "fast-json"
Provides-Extra: all
Requires-Dist: click>=8.0.0; extra == "all"
Requires-Dist: werkzeug>=2.0.0; extra == "all"
Requires-Dist: redis>=4.0.0; extra == "all"
Requires-Dist: structlog>=22.0.0; extra == "all"
Requires-Dist: orjson>=3.8.0; extra == "all"
Dynamic: author
Dynamic: home-page
Dynamic: license-file
Dynamic: requires-python
